vending machiene.srcs/sources_1/new/vending_machine_18105070.v
`timescale 1ns / 1ps
//////////////////////////////////////////////////////////////////////////////////
// Company: 
// Engineer: 
// 
// Create Date: 18.05.2023 01:20:09
// Design Name: 
// Module Name: vending_machine_18105070
// Project Name: 
// Target Devices: 
// Tool Versions: 
// Description: 
// 
// Dependencies: 
// 
// Revision:
// Revision 0.01 - File Created
// Additional Comments:
// 
//////////////////////////////////////////////////////////////////////////////////


module vending_machine_18105070(
  input clk,
  input rst,
  input [1:0]in, //input, 01 = 5 rs, 10 = 10 rs //00 means nothing was added, 01 means 5 rupee was aded i.e. given as input
  output reg out,//1-->product is given to user, 0-->no prod
  output reg[1:0] change,//tells change, can be 5,10 or 0 as prod cost is 15 and we only have 5 and 10 as coins
  output reg[1:0] c_state,
  output reg[1:0] n_state
  );

parameter s0 = 2'b00;//we take 3 params for 3states
parameter s1 = 2'b01;
parameter s2 = 2'b10;
  
  //reg[1:0] c_state,n_state;//to store current and next state
  
  always@ (posedge clk)
    begin
      if(rst == 1)
        begin
          c_state = 0;
          n_state = 0;
          change = 2'b00;
        end
      else
        c_state = n_state;//we need this
      
      case(c_state)
        s0: //state 0 : 0 rs
        if(in == 0)
          begin
            n_state = s0;
            out = 0;
            change = 2'b00;
          end
        else if(in == 2'b01)
          begin
            n_state = s1;
            out = 0;
            change = 2'b00;
          end
        else if(in == 2'b10)
          begin
            n_state = s2;
            out = 0;
            change = 2'b00;
          end
        s1:  //state 1 : 5 rs
        if(in == 0)
          begin
            n_state = s0;
            out = 0;
            change = 2'b01; //change returned 5 rs
          end
        else if(in == 2'b01)
          begin
            n_state = s2;
            out = 0;
            change = 2'b00;
          end
        else if(in == 2'b10)
          begin
            n_state = s0;
            out = 1;
            change = 2'b00;
          end
        s2:  //state 2 : 10 rs
        if(in == 0)
          begin
            n_state = s0;
            out = 0;
            change = 2'b10;
          end
        else if(in == 2'b01)
          begin
            n_state = s0;
            out = 1;
            change = 2'b00;
          end
        else if(in == 2'b10)
          begin
            n_state = s0;
            out = 1;
            change = 2'b01; //change returned 5 rs and 1 bottle
          end
      endcase
    end 
endmodule

vending machiene.srcs/sim_1/new/vending_machine_tb.v
module vending_machine_tb;
  
  //inputs
  reg clk;
  reg[1:0] in;
  reg rst;
  
  //output
  wire out;
  wire[1:0] change;
  wire[1:0] c_state;
  wire[1:0] n_state;
  
  
  //instantiate our module
  vending_machine_18105070 uut(
    .clk(clk),
    .rst(rst),
    .in(in),
    .out(out),
    .change(change),
    .c_state(c_state),
    .n_state(n_state)
  );
  
  initial begin
    
    //initialise inputs
   $dumpfile("vending_machine_18105070.vcd");
    $dumpvars(0,vending_machine_tb);
    rst = 1;
    clk = 0;
    
    #6 rst = 0;
    
    in = 10;
    #11 in = 10; 
    #16 in = 1;
    #25 $finish;
    
  end
  always #5 clk = ~clk;
  
endmodule

vending machiene.sim/sim_1/behav/xsim/vending_machine_18105070.vcd
$date
   Thu May 18 12:33:07 2023
$end
$version
  2018.3
$end
$timescale
  1ps
$end
$scope module vending_machine_tb $end
$var reg 1 ! clk $end
$var reg 2 " in [1:0] $end
$var reg 1 # rst $end
$var wire 1 $ out $end
$var wire 2 % change [1:0] $end
$var wire 2 & c_state [1:0] $end
$var wire 2 ' n_state [1:0] $end
$scope module uut $end
$var wire 1 ( clk $end
$var wire 1 ) rst $end
$var wire 2 * in [1:0] $end
$var reg 1 + out $end
$var reg 2 , change [1:0] $end
$var reg 2 - c_state [1:0] $end
$var reg 2 . n_state [1:0] $end
$var parameter 2 / s0 [1:0] $end
$var parameter 2 0 s1 [1:0] $end
$var parameter 2 1 s2 [1:0] $end
$upscope $end
$upscope $end
$enddefinitions $end
#0
$dumpvars
0!
bx "
1#
x$
bx %
bx &
bx '
0(
1)
bx *
x+
bx ,
bx -
bx .
b0 /
b1 0
b10 1
$end
#5000
1!
b0 %
b0 &
b0 '
1(
b0 ,
b0 -
b0 .
#6000
b1 "
0#
0)
b1 *
#10000
0!
0(
#15000
1!
0$
b1 '
1(
0+
b0 ,
b0 -
b1 .
#17000
b1 "
#20000
0!
0(
#25000
1!
b1 &
b10 '
1(
0+
b0 ,
b1 -
b10 .
#30000
0!
0(
#33000
b0 "
b0 *
#35000
1!
b10 %
b10 &
b0 '
1(
0+
b10 ,
b10 -
b0 .
#40000
0!
0(
#45000
1!
b0 %
b0 &
1(
0+
b0 ,
b0 -
b0 .
#50000
0!
0(
#55000
1!
1(
0+
b0 ,
b0 -
b0 .
